{
	"credit": "Made by Satellence with Blockbench",
	"texture_size": [32, 32],
	"textures": {
        "0": "block/nature/flowers/allium",
        "particle": "block/nature/flowers/allium"
	},
	"elements": [
		{
			"name": "Steam",
			"from": [5.96364, 0, 11.96364],
			"to": [6.46364, 10.5, 12.46364],
			"rotation": {"angle": 22.5, "axis": "y", "origin": [6.21364, 13.77273, 12.25]},
			"faces": {
				"north": {"uv": [1.25, 2.75, 1.5, 8], "texture": "#0"},
				"east": {"uv": [1.25, 2.75, 1.5, 8], "texture": "#0"},
				"south": {"uv": [1.25, 2.75, 1.5, 8], "texture": "#0"},
				"west": {"uv": [1.25, 2.75, 1.5, 8], "texture": "#0"}
			}
		},
		{
			"name": "FlowerBase",
			"from": [5.46364, 10.5, 11.46364],
			"to": [6.96364, 11, 12.96364],
			"rotation": {"angle": 22.5, "axis": "y", "origin": [6.21364, 11.77273, 12.25]},
			"faces": {
				"north": {"uv": [0, 1.75, 0.75, 2], "texture": "#0"},
				"east": {"uv": [0, 1.75, 0.75, 2], "texture": "#0"},
				"south": {"uv": [0, 1.75, 0.75, 2], "texture": "#0"},
				"west": {"uv": [0, 1.75, 0.75, 2], "texture": "#0"},
				"down": {"uv": [0, 1.75, 0.75, 2.5], "rotation": 90, "texture": "#0"}
			}
		},
		{
			"name": "FlowerCube",
			"from": [4.96364, 11, 10.96364],
			"to": [7.46364, 14, 13.46364],
			"rotation": {"angle": 22.5, "axis": "y", "origin": [6.21364, 11.77273, 12.25]},
			"faces": {
				"north": {"uv": [7.25, 0.75, 8.5, 2], "texture": "#0"},
				"east": {"uv": [10.25, 0.5, 11.5, 1.75], "texture": "#0"},
				"south": {"uv": [7.25, 0.75, 8.5, 2], "texture": "#0"},
				"west": {"uv": [7.5, 0.5, 8.75, 1.75], "texture": "#0"},
				"up": {"uv": [10, 0.75, 11.25, 2], "rotation": 270, "texture": "#0"},
				"down": {"uv": [4.5, 0, 5.75, 1.25], "rotation": 90, "texture": "#0"}
			}
		},
		{
			"name": "FlowerExtra",
			"from": [2.96364, 10, 12.26364],
			"to": [9.46364, 15.5, 12.26364],
			"rotation": {"angle": 22.5, "axis": "y", "origin": [6.21364, 11.77273, 12.25]},
			"faces": {
				"north": {"uv": [9.5, 0, 6.25, 2.75], "texture": "#0"},
				"south": {"uv": [6.25, 0, 9.5, 2.75], "texture": "#0"}
			}
		},
		{
			"name": "FlowerExtra",
			"from": [2.95842, 10, 12.2626],
			"to": [9.45842, 15.5, 12.2626],
			"rotation": {"angle": 45, "axis": "y", "origin": [6.21364, 11.77273, 12.25]},
			"faces": {
				"north": {"uv": [9.5, 0, 6.25, 2.75], "texture": "#0"},
				"south": {"uv": [6.25, 0, 9.5, 2.75], "texture": "#0"}
			}
		},
		{
			"name": "FlowerExtra",
			"from": [6.21364, 10, 9.01364],
			"to": [6.21364, 15.5, 15.51364],
			"rotation": {"angle": 22.5, "axis": "y", "origin": [6.21364, 11.77273, 12.25]},
			"faces": {
				"east": {"uv": [9.5, 0, 12.75, 2.75], "texture": "#0"},
				"west": {"uv": [12.75, 0, 9.5, 2.75], "texture": "#0"}
			}
		},
		{
			"name": "FlowerExtra",
			"from": [6.21885, 10, 9.0126],
			"to": [6.21885, 15.5, 15.5126],
			"rotation": {"angle": 0, "axis": "y", "origin": [6.21364, 11.77273, 12.25]},
			"faces": {
				"east": {"uv": [9.5, 0, 12.75, 2.75], "texture": "#0"},
				"west": {"uv": [12.75, 0, 9.5, 2.75], "texture": "#0"}
			}
		},
		{
			"name": "FlowerExtra",
			"from": [2.97328, 10, 12.25964],
			"to": [9.47328, 15.5, 12.25964],
			"rotation": {"angle": -22.5, "axis": "y", "origin": [6.21364, 11.77273, 12.25]},
			"faces": {
				"north": {"uv": [12.75, 0, 16, 2.75], "texture": "#0"},
				"south": {"uv": [16, 0, 12.75, 2.75], "texture": "#0"}
			}
		},
		{
			"name": "FlowerExtra",
			"from": [6.20842, 10, 9.0126],
			"to": [6.20842, 15.5, 15.5126],
			"rotation": {"angle": 45, "axis": "y", "origin": [6.21364, 11.77273, 12.25]},
			"faces": {
				"east": {"uv": [16, 0, 12.75, 2.75], "texture": "#0"},
				"west": {"uv": [12.75, 0, 16, 2.75], "texture": "#0"}
			}
		},
		{
			"name": "FlowerExtra",
			"from": [2.96885, 10, 12.2626],
			"to": [9.46885, 15.5, 12.2626],
			"rotation": {"angle": 0, "axis": "y", "origin": [6.21364, 11.77273, 12.25]},
			"faces": {
				"north": {"uv": [12.75, 0, 16, 2.75], "texture": "#0"},
				"south": {"uv": [16, 0, 12.75, 2.75], "texture": "#0"}
			}
		},
		{
			"name": "FlowerExtra",
			"from": [6.22328, 10, 9.00964],
			"to": [6.22328, 15.5, 15.50964],
			"rotation": {"angle": -22.5, "axis": "y", "origin": [6.21364, 11.77273, 12.25]},
			"faces": {
				"east": {"uv": [16, 0, 12.75, 2.75], "texture": "#0"},
				"west": {"uv": [12.75, 0, 16, 2.75], "texture": "#0"}
			}
		},
		{
			"name": "Steam",
			"from": [3.92727, 0, 7],
			"to": [4.42727, 10.5, 7.5],
			"rotation": {"angle": 45, "axis": "y", "origin": [4.21364, 13.77273, 7.25]},
			"faces": {
				"north": {"uv": [1.25, 2.75, 1.5, 8], "texture": "#0"},
				"east": {"uv": [1.25, 2.75, 1.5, 8], "texture": "#0"},
				"south": {"uv": [1.25, 2.75, 1.5, 8], "texture": "#0"},
				"west": {"uv": [1.25, 2.75, 1.5, 8], "texture": "#0"}
			}
		},
		{
			"name": "FlowerBase",
			"from": [3.42727, 10.5, 6.5],
			"to": [4.92727, 11, 8],
			"rotation": {"angle": 45, "axis": "y", "origin": [4.21364, 11.77273, 7.25]},
			"faces": {
				"north": {"uv": [0, 1.75, 0.75, 2], "texture": "#0"},
				"east": {"uv": [0, 1.75, 0.75, 2], "texture": "#0"},
				"south": {"uv": [0, 1.75, 0.75, 2], "texture": "#0"},
				"west": {"uv": [0, 1.75, 0.75, 2], "texture": "#0"},
				"down": {"uv": [0, 1.75, 0.75, 2.5], "rotation": 180, "texture": "#0"}
			}
		},
		{
			"name": "FlowerCube",
			"from": [2.92727, 11, 6],
			"to": [5.42727, 14, 8.5],
			"rotation": {"angle": 45, "axis": "y", "origin": [4.21364, 11.77273, 7.25]},
			"faces": {
				"north": {"uv": [10.25, 0.5, 11.5, 1.75], "texture": "#0"},
				"east": {"uv": [7.25, 0.75, 8.5, 2], "texture": "#0"},
				"south": {"uv": [7.5, 0.5, 8.75, 1.75], "texture": "#0"},
				"west": {"uv": [7.25, 0.75, 8.5, 2], "texture": "#0"},
				"up": {"uv": [10, 0.75, 11.25, 2], "rotation": 180, "texture": "#0"},
				"down": {"uv": [3.25, 0, 4.5, 1.25], "rotation": 180, "texture": "#0"}
			}
		},
		{
			"name": "FlowerExtra",
			"from": [4.22727, 10, 4],
			"to": [4.22727, 15.5, 10.5],
			"rotation": {"angle": 45, "axis": "y", "origin": [4.21364, 11.77273, 7.25]},
			"faces": {
				"east": {"uv": [6.25, 0, 9.5, 2.75], "texture": "#0"},
				"west": {"uv": [9.5, 0, 6.25, 2.75], "texture": "#0"}
			}
		},
		{
			"name": "FlowerExtra",
			"from": [0.96885, 10, 7.2374],
			"to": [7.46885, 15.5, 7.2374],
			"rotation": {"angle": -22.5, "axis": "y", "origin": [4.21364, 11.77273, 7.25]},
			"faces": {
				"north": {"uv": [6.25, 0, 9.5, 2.75], "texture": "#0"},
				"south": {"uv": [9.5, 0, 6.25, 2.75], "texture": "#0"}
			}
		},
		{
			"name": "FlowerExtra",
			"from": [0.97727, 10, 7.25],
			"to": [7.47727, 15.5, 7.25],
			"rotation": {"angle": 45, "axis": "y", "origin": [4.21364, 11.77273, 7.25]},
			"faces": {
				"north": {"uv": [9.5, 0, 12.75, 2.75], "texture": "#0"},
				"south": {"uv": [12.75, 0, 9.5, 2.75], "texture": "#0"}
			}
		},
		{
			"name": "FlowerExtra",
			"from": [0.97623, 10, 7.24478],
			"to": [7.47623, 15.5, 7.24478],
			"rotation": {"angle": 22.5, "axis": "y", "origin": [4.21364, 11.77273, 7.25]},
			"faces": {
				"north": {"uv": [9.5, 0, 12.75, 2.75], "texture": "#0"},
				"south": {"uv": [12.75, 0, 9.5, 2.75], "texture": "#0"}
			}
		},
		{
			"name": "FlowerExtra",
			"from": [4.22328, 10, 3.99036],
			"to": [4.22328, 15.5, 10.49036],
			"rotation": {"angle": 0, "axis": "y", "origin": [4.21364, 11.77273, 7.25]},
			"faces": {
				"east": {"uv": [16, 0, 12.75, 2.75], "texture": "#0"},
				"west": {"uv": [12.75, 0, 16, 2.75], "texture": "#0"}
			}
		},
		{
			"name": "FlowerExtra",
			"from": [4.21885, 10, 3.9874],
			"to": [4.21885, 15.5, 10.4874],
			"rotation": {"angle": -22.5, "axis": "y", "origin": [4.21364, 11.77273, 7.25]},
			"faces": {
				"east": {"uv": [12.75, 0, 16, 2.75], "texture": "#0"},
				"west": {"uv": [16, 0, 12.75, 2.75], "texture": "#0"}
			}
		},
		{
			"name": "FlowerExtra",
			"from": [4.22623, 10, 3.99478],
			"to": [4.22623, 15.5, 10.49478],
			"rotation": {"angle": 22.5, "axis": "y", "origin": [4.21364, 11.77273, 7.25]},
			"faces": {
				"east": {"uv": [16, 0, 12.75, 2.75], "texture": "#0"},
				"west": {"uv": [12.75, 0, 16, 2.75], "texture": "#0"}
			}
		},
		{
			"name": "FlowerExtra",
			"from": [0.97328, 10, 7.24036],
			"to": [7.47328, 15.5, 7.24036],
			"rotation": {"angle": 0, "axis": "y", "origin": [4.21364, 11.77273, 7.25]},
			"faces": {
				"north": {"uv": [16, 0, 12.75, 2.75], "texture": "#0"},
				"south": {"uv": [12.75, 0, 16, 2.75], "texture": "#0"}
			}
		},
		{
			"name": "Steam",
			"from": [9.96364, 0, 5.03636],
			"to": [10.46364, 7.5, 5.53636],
			"rotation": {"angle": -45, "axis": "y", "origin": [10.21364, 13.77273, 5.25]},
			"faces": {
				"north": {"uv": [1.25, 4.25, 1.5, 8], "texture": "#0"},
				"east": {"uv": [1.25, 4.25, 1.5, 8], "texture": "#0"},
				"south": {"uv": [1.25, 4.25, 1.5, 8], "texture": "#0"},
				"west": {"uv": [1.25, 4.25, 1.5, 8], "texture": "#0"}
			}
		},
		{
			"name": "FlowerBase",
			"from": [9.46364, 7.5, 4.53636],
			"to": [10.96364, 8, 6.03636],
			"rotation": {"angle": -45, "axis": "y", "origin": [10.21364, 8.77273, 5.25]},
			"faces": {
				"north": {"uv": [0, 1.75, 0.75, 2], "texture": "#0"},
				"east": {"uv": [0, 1.75, 0.75, 2], "texture": "#0"},
				"south": {"uv": [0, 1.75, 0.75, 2], "texture": "#0"},
				"west": {"uv": [0, 1.75, 0.75, 2], "texture": "#0"},
				"down": {"uv": [0, 1.75, 0.75, 2.5], "rotation": 270, "texture": "#0"}
			}
		},
		{
			"name": "FlowerCube",
			"from": [8.96364, 8, 4.03636],
			"to": [11.46364, 11, 6.53636],
			"rotation": {"angle": -45, "axis": "y", "origin": [10.21364, 8.77273, 5.25]},
			"faces": {
				"north": {"uv": [7.25, 0.75, 8.5, 2], "texture": "#0"},
				"east": {"uv": [7.5, 0.5, 8.75, 1.75], "texture": "#0"},
				"south": {"uv": [7.25, 0.75, 8.5, 2], "texture": "#0"},
				"west": {"uv": [10.25, 0.5, 11.5, 1.75], "texture": "#0"},
				"up": {"uv": [10, 0.75, 11.25, 2], "rotation": 90, "texture": "#0"},
				"down": {"uv": [4.5, 0, 5.75, 1.25], "rotation": 270, "texture": "#0"}
			}
		},
		{
			"name": "FlowerExtra",
			"from": [6.96364, 7, 5.23636],
			"to": [13.46364, 12.5, 5.23636],
			"rotation": {"angle": -45, "axis": "y", "origin": [10.21364, 8.77273, 5.25]},
			"faces": {
				"north": {"uv": [6.25, 0, 9.5, 2.75], "texture": "#0"},
				"south": {"uv": [9.5, 0, 6.25, 2.75], "texture": "#0"}
			}
		},
		{
			"name": "FlowerExtra",
			"from": [6.96885, 7, 5.2374],
			"to": [13.46885, 12.5, 5.2374],
			"rotation": {"angle": -22.5, "axis": "y", "origin": [10.21364, 8.77273, 5.25]},
			"faces": {
				"north": {"uv": [6.25, 0, 9.5, 2.75], "texture": "#0"},
				"south": {"uv": [9.5, 0, 6.25, 2.75], "texture": "#0"}
			}
		},
		{
			"name": "FlowerExtra",
			"from": [10.21364, 7, 1.98636],
			"to": [10.21364, 12.5, 8.48636],
			"rotation": {"angle": -45, "axis": "y", "origin": [10.21364, 8.77273, 5.25]},
			"faces": {
				"east": {"uv": [12.75, 0, 9.5, 2.75], "texture": "#0"},
				"west": {"uv": [9.5, 0, 12.75, 2.75], "texture": "#0"}
			}
		},
		{
			"name": "FlowerExtra",
			"from": [6.97623, 7, 5.24478],
			"to": [13.47623, 12.5, 5.24478],
			"rotation": {"angle": 22.5, "axis": "y", "origin": [10.21364, 8.77273, 5.25]},
			"faces": {
				"north": {"uv": [9.5, 0, 12.75, 2.75], "texture": "#0"},
				"south": {"uv": [12.75, 0, 9.5, 2.75], "texture": "#0"}
			}
		},
		{
			"name": "FlowerExtra",
			"from": [10.22328, 7, 1.99036],
			"to": [10.22328, 12.5, 8.49036],
			"rotation": {"angle": 0, "axis": "y", "origin": [10.21364, 8.77273, 5.25]},
			"faces": {
				"east": {"uv": [16, 0, 12.75, 2.75], "texture": "#0"},
				"west": {"uv": [12.75, 0, 16, 2.75], "texture": "#0"}
			}
		},
		{
			"name": "FlowerExtra",
			"from": [10.21885, 7, 1.9874],
			"to": [10.21885, 12.5, 8.4874],
			"rotation": {"angle": -22.5, "axis": "y", "origin": [10.21364, 8.77273, 5.25]},
			"faces": {
				"east": {"uv": [12.75, 0, 16, 2.75], "texture": "#0"},
				"west": {"uv": [16, 0, 12.75, 2.75], "texture": "#0"}
			}
		},
		{
			"name": "FlowerExtra",
			"from": [10.22623, 7, 1.99478],
			"to": [10.22623, 12.5, 8.49478],
			"rotation": {"angle": 22.5, "axis": "y", "origin": [10.21364, 8.77273, 5.25]},
			"faces": {
				"east": {"uv": [16, 0, 12.75, 2.75], "texture": "#0"},
				"west": {"uv": [12.75, 0, 16, 2.75], "texture": "#0"}
			}
		},
		{
			"name": "FlowerExtra",
			"from": [6.97328, 7, 5.24036],
			"to": [13.47328, 12.5, 5.24036],
			"rotation": {"angle": 0, "axis": "y", "origin": [10.21364, 8.77273, 5.25]},
			"faces": {
				"north": {"uv": [16, 0, 12.75, 2.75], "texture": "#0"},
				"south": {"uv": [12.75, 0, 16, 2.75], "texture": "#0"}
			}
		},
		{
			"name": "Steam",
			"from": [9.92727, 0, 10],
			"to": [10.42727, 9.5, 10.5],
			"rotation": {"angle": 45, "axis": "y", "origin": [10.21364, 13.77273, 10.25]},
			"faces": {
				"north": {"uv": [2.25, 3.25, 2.5, 8], "texture": "#0"},
				"east": {"uv": [2.25, 3.25, 2.5, 8], "texture": "#0"},
				"south": {"uv": [2.25, 3.25, 2.5, 8], "texture": "#0"},
				"west": {"uv": [2.25, 3.25, 2.5, 8], "texture": "#0"}
			}
		},
		{
			"name": "FlowerBase",
			"from": [9.42727, 9.5, 9.5],
			"to": [10.92727, 10, 11],
			"rotation": {"angle": 45, "axis": "y", "origin": [10.21364, 10.77273, 10.25]},
			"faces": {
				"north": {"uv": [0, 1.75, 0.75, 2], "texture": "#0"},
				"east": {"uv": [0, 1.75, 0.75, 2], "texture": "#0"},
				"south": {"uv": [0, 1.75, 0.75, 2], "texture": "#0"},
				"west": {"uv": [0, 1.75, 0.75, 2], "texture": "#0"},
				"down": {"uv": [0, 1.75, 0.75, 2.5], "rotation": 180, "texture": "#0"}
			}
		},
		{
			"name": "FlowerCube",
			"from": [8.92727, 10, 9],
			"to": [11.42727, 13, 11.5],
			"rotation": {"angle": 45, "axis": "y", "origin": [10.21364, 10.77273, 10.25]},
			"faces": {
				"north": {"uv": [10.25, 0.5, 11.5, 1.75], "texture": "#0"},
				"east": {"uv": [7.25, 0.75, 8.5, 2], "texture": "#0"},
				"south": {"uv": [7.5, 0.5, 8.75, 1.75], "texture": "#0"},
				"west": {"uv": [7.25, 0.75, 8.5, 2], "texture": "#0"},
				"up": {"uv": [10, 0.75, 11.25, 2], "rotation": 180, "texture": "#0"},
				"down": {"uv": [4.5, 0, 5.75, 1.25], "rotation": 180, "texture": "#0"}
			}
		},
		{
			"name": "FlowerExtra",
			"from": [10.22727, 9, 7],
			"to": [10.22727, 14.5, 13.5],
			"rotation": {"angle": 45, "axis": "y", "origin": [10.21364, 10.77273, 10.25]},
			"faces": {
				"east": {"uv": [6.25, 0, 9.5, 2.75], "texture": "#0"},
				"west": {"uv": [9.5, 0, 6.25, 2.75], "texture": "#0"}
			}
		},
		{
			"name": "FlowerExtra",
			"from": [6.96886, 9, 10.23741],
			"to": [13.46886, 14.5, 10.23741],
			"rotation": {"angle": -22.5, "axis": "y", "origin": [10.21364, 10.77273, 10.25]},
			"faces": {
				"north": {"uv": [6.25, 0, 9.5, 2.75], "texture": "#0"},
				"south": {"uv": [9.5, 0, 6.25, 2.75], "texture": "#0"}
			}
		},
		{
			"name": "FlowerExtra",
			"from": [6.97727, 9, 10.25],
			"to": [13.47727, 14.5, 10.25],
			"rotation": {"angle": 45, "axis": "y", "origin": [10.21364, 10.77273, 10.25]},
			"faces": {
				"north": {"uv": [9.5, 0, 12.75, 2.75], "texture": "#0"},
				"south": {"uv": [12.75, 0, 9.5, 2.75], "texture": "#0"}
			}
		},
		{
			"name": "FlowerExtra",
			"from": [6.97623, 9, 10.24478],
			"to": [13.47623, 14.5, 10.24478],
			"rotation": {"angle": 22.5, "axis": "y", "origin": [10.21364, 10.77273, 10.25]},
			"faces": {
				"north": {"uv": [9.5, 0, 12.75, 2.75], "texture": "#0"},
				"south": {"uv": [12.75, 0, 9.5, 2.75], "texture": "#0"}
			}
		},
		{
			"name": "FlowerExtra",
			"from": [10.22328, 9, 6.99036],
			"to": [10.22328, 14.5, 13.49036],
			"rotation": {"angle": 0, "axis": "y", "origin": [10.21364, 10.77273, 10.25]},
			"faces": {
				"east": {"uv": [16, 0, 12.75, 2.75], "texture": "#0"},
				"west": {"uv": [12.75, 0, 16, 2.75], "texture": "#0"}
			}
		},
		{
			"name": "FlowerExtra",
			"from": [10.21886, 9, 6.98741],
			"to": [10.21886, 14.5, 13.48741],
			"rotation": {"angle": -22.5, "axis": "y", "origin": [10.21364, 10.77273, 10.25]},
			"faces": {
				"east": {"uv": [12.75, 0, 16, 2.75], "texture": "#0"},
				"west": {"uv": [16, 0, 12.75, 2.75], "texture": "#0"}
			}
		},
		{
			"name": "FlowerExtra",
			"from": [10.22623, 9, 6.99478],
			"to": [10.22623, 14.5, 13.49478],
			"rotation": {"angle": 22.5, "axis": "y", "origin": [10.21364, 10.77273, 10.25]},
			"faces": {
				"east": {"uv": [16, 0, 12.75, 2.75], "texture": "#0"},
				"west": {"uv": [12.75, 0, 16, 2.75], "texture": "#0"}
			}
		},
		{
			"name": "FlowerExtra",
			"from": [6.97328, 9, 10.24036],
			"to": [13.47328, 14.5, 10.24036],
			"rotation": {"angle": 0, "axis": "y", "origin": [10.21364, 10.77273, 10.25]},
			"faces": {
				"north": {"uv": [16, 0, 12.75, 2.75], "texture": "#0"},
				"south": {"uv": [12.75, 0, 16, 2.75], "texture": "#0"}
			}
		},
		{
			"name": "Grass",
			"from": [11.41758, 0, 7.96716],
			"to": [11.41758, 4.5, 15.46716],
			"rotation": {"angle": 45, "axis": "y", "origin": [11.41758, 2.25, 11.71716]},
			"faces": {
				"east": {"uv": [10, 5.25, 6.25, 7.5], "texture": "#0"},
				"west": {"uv": [6.25, 5.25, 10, 7.5], "texture": "#0"}
			}
		},
		{
			"name": "Grass",
			"from": [7.41758, 0, 7.96716],
			"to": [7.41758, 4.5, 15.46716],
			"rotation": {"angle": -45, "axis": "y", "origin": [7.41758, 2.25, 11.71716]},
			"faces": {
				"east": {"uv": [10, 5.25, 6.25, 7.5], "texture": "#0"},
				"west": {"uv": [6.25, 5.25, 10, 7.5], "texture": "#0"}
			}
		},
		{
			"name": "Grass",
			"from": [0.66758, 0, 9.71716],
			"to": [8.16758, 4.5, 9.71716],
			"rotation": {"angle": 22.5, "axis": "y", "origin": [4.41758, 2.25, 9.71716]},
			"faces": {
				"north": {"uv": [6.25, 5.25, 10, 7.5], "texture": "#0"},
				"south": {"uv": [10, 5.25, 6.25, 7.5], "texture": "#0"}
			}
		},
		{
			"name": "Grass",
			"from": [7.66758, 0, 5.71716],
			"to": [15.16758, 4.5, 5.71716],
			"rotation": {"angle": 22.5, "axis": "y", "origin": [11.41758, 2.25, 5.71716]},
			"faces": {
				"north": {"uv": [6.25, 5.25, 10, 7.5], "texture": "#0"},
				"south": {"uv": [10, 5.25, 6.25, 7.5], "texture": "#0"}
			}
		},
		{
			"name": "Grass",
			"from": [1.66758, 0, 4.71716],
			"to": [9.16758, 4.5, 4.71716],
			"rotation": {"angle": -22.5, "axis": "y", "origin": [5.41758, 2.25, 4.71716]},
			"faces": {
				"north": {"uv": [6.25, 5.25, 10, 7.5], "texture": "#0"},
				"south": {"uv": [10, 5.25, 6.25, 7.5], "texture": "#0"}
			}
		},
		{
			"name": "Grass",
			"from": [4.66758, 1, 7.71716],
			"to": [12.16758, 5.5, 7.71716],
			"rotation": {"angle": -22.5, "axis": "y", "origin": [8.41758, 2.25, 7.71716]},
			"faces": {
				"north": {"uv": [6.25, 5.25, 10, 7.5], "texture": "#0"},
				"south": {"uv": [10, 5.25, 6.25, 7.5], "texture": "#0"}
			}
		},
		{
			"name": "Grass",
			"from": [7.66758, 0, 11.71716],
			"to": [15.16758, 4.5, 11.71716],
			"rotation": {"angle": 0, "axis": "y", "origin": [11.41758, 2.25, 11.71716]},
			"faces": {
				"north": {"uv": [10, 5.25, 6.25, 7.5], "texture": "#0"},
				"south": {"uv": [6.25, 5.25, 10, 7.5], "texture": "#0"}
			}
		},
		{
			"name": "Grass",
			"from": [7.41758, 0, 7.96716],
			"to": [7.41758, 4.5, 15.46716],
			"rotation": {"angle": 0, "axis": "y", "origin": [7.41758, 2.25, 11.71716]},
			"faces": {
				"east": {"uv": [10, 5.25, 6.25, 7.5], "texture": "#0"},
				"west": {"uv": [6.25, 5.25, 10, 7.5], "texture": "#0"}
			}
		},
		{
			"name": "Grass",
			"from": [4.41758, 0, 5.96716],
			"to": [4.41758, 4.5, 13.46716],
			"rotation": {"angle": -22.5, "axis": "y", "origin": [4.41758, 2.25, 9.71716]},
			"faces": {
				"east": {"uv": [10, 5.25, 6.25, 7.5], "texture": "#0"},
				"west": {"uv": [6.25, 5.25, 10, 7.5], "texture": "#0"}
			}
		},
		{
			"name": "Grass",
			"from": [11.41758, 0, 1.96716],
			"to": [11.41758, 4.5, 9.46716],
			"rotation": {"angle": -22.5, "axis": "y", "origin": [11.41758, 2.25, 5.71716]},
			"faces": {
				"east": {"uv": [10, 5.25, 6.25, 7.5], "texture": "#0"},
				"west": {"uv": [6.25, 5.25, 10, 7.5], "texture": "#0"}
			}
		},
		{
			"name": "Grass",
			"from": [1.66758, 0, 5.71716],
			"to": [9.16758, 4.5, 5.71716],
			"rotation": {"angle": 22.5, "axis": "y", "origin": [5.41758, 2.25, 5.71716]},
			"faces": {
				"north": {"uv": [6.25, 5.25, 10, 7.5], "texture": "#0"},
				"south": {"uv": [10, 5.25, 6.25, 7.5], "texture": "#0"}
			}
		},
		{
			"name": "Grass",
			"from": [4.66758, 1, 7.71716],
			"to": [12.16758, 5.5, 7.71716],
			"rotation": {"angle": 22.5, "axis": "y", "origin": [8.41758, 2.25, 7.71716]},
			"faces": {
				"north": {"uv": [6.25, 5.25, 10, 7.5], "texture": "#0"},
				"south": {"uv": [10, 5.25, 6.25, 7.5], "texture": "#0"}
			}
		},
		{
			"name": "Grass",
			"from": [7.66758, 0, 11.71716],
			"to": [15.16758, 4.5, 11.71716],
			"rotation": {"angle": 45, "axis": "y", "origin": [11.41758, 2.25, 11.71716]},
			"faces": {
				"north": {"uv": [14, 5.25, 10.25, 7.5], "texture": "#0"},
				"south": {"uv": [10.25, 5.25, 14, 7.5], "texture": "#0"}
			}
		},
		{
			"name": "Grass",
			"from": [3.66758, 0, 11.71716],
			"to": [11.16758, 4.5, 11.71716],
			"rotation": {"angle": -45, "axis": "y", "origin": [7.41758, 2.25, 11.71716]},
			"faces": {
				"north": {"uv": [14, 5.25, 10.25, 7.5], "texture": "#0"},
				"south": {"uv": [10.25, 5.25, 14, 7.5], "texture": "#0"}
			}
		},
		{
			"name": "Grass",
			"from": [4.41758, 0, 5.96716],
			"to": [4.41758, 4.5, 13.46716],
			"rotation": {"angle": 22.5, "axis": "y", "origin": [4.41758, 2.25, 9.71716]},
			"faces": {
				"east": {"uv": [14, 5.25, 10.25, 7.5], "texture": "#0"},
				"west": {"uv": [10.25, 5.25, 14, 7.5], "texture": "#0"}
			}
		},
		{
			"name": "Grass",
			"from": [11.41758, 0, 0.96716],
			"to": [11.41758, 4.5, 8.46716],
			"rotation": {"angle": 22.5, "axis": "y", "origin": [11.41758, 2.25, 4.71716]},
			"faces": {
				"east": {"uv": [14, 5.25, 10.25, 7.5], "texture": "#0"},
				"west": {"uv": [10.25, 5.25, 14, 7.5], "texture": "#0"}
			}
		},
		{
			"name": "Grass",
			"from": [13.41758, 0, 4.96716],
			"to": [13.41758, 4.5, 12.46716],
			"rotation": {"angle": 0, "axis": "y", "origin": [11.41758, 2.25, 4.71716]},
			"faces": {
				"east": {"uv": [10.25, 5.25, 14, 7.5], "texture": "#0"},
				"west": {"uv": [14, 5.25, 10.25, 7.5], "texture": "#0"}
			}
		},
		{
			"name": "Grass",
			"from": [12.41758, 0, 4.96716],
			"to": [12.41758, 4.5, 12.46716],
			"rotation": {"angle": -22.5, "axis": "y", "origin": [13.41758, 2.25, 8.71716]},
			"faces": {
				"east": {"uv": [6.25, 5.25, 10, 7.5], "texture": "#0"},
				"west": {"uv": [10, 5.25, 6.25, 7.5], "texture": "#0"}
			}
		},
		{
			"name": "Grass",
			"from": [5.41758, 0, 1.96716],
			"to": [5.41758, 4.5, 9.46716],
			"rotation": {"angle": -22.5, "axis": "y", "origin": [5.41758, 2.25, 5.71716]},
			"faces": {
				"east": {"uv": [14, 5.25, 10.25, 7.5], "texture": "#0"},
				"west": {"uv": [10.25, 5.25, 14, 7.5], "texture": "#0"}
			}
		},
		{
			"name": "Grass",
			"from": [8.41758, 0, 3.96716],
			"to": [8.41758, 4.5, 11.46716],
			"rotation": {"angle": -22.5, "axis": "y", "origin": [8.41758, 2.25, 7.71716]},
			"faces": {
				"east": {"uv": [14, 5.25, 10.25, 7.5], "texture": "#0"},
				"west": {"uv": [10.25, 5.25, 14, 7.5], "texture": "#0"}
			}
		},
		{
			"name": "Grass",
			"from": [11.41758, 0, 7.96716],
			"to": [11.41758, 4.5, 15.46716],
			"rotation": {"angle": 0, "axis": "y", "origin": [11.41758, 2.25, 11.71716]},
			"faces": {
				"east": {"uv": [10.25, 5.25, 14, 7.5], "texture": "#0"},
				"west": {"uv": [14, 5.25, 10.25, 7.5], "texture": "#0"}
			}
		},
		{
			"name": "Grass",
			"from": [3.66758, 1, 11.71716],
			"to": [11.16758, 5.5, 11.71716],
			"rotation": {"angle": 0, "axis": "y", "origin": [7.41758, 2.25, 11.71716]},
			"faces": {
				"north": {"uv": [14, 5.25, 10.25, 7.5], "texture": "#0"},
				"south": {"uv": [10.25, 5.25, 14, 7.5], "texture": "#0"}
			}
		},
		{
			"name": "Grass",
			"from": [0.66758, 0, 9.71716],
			"to": [8.16758, 4.5, 9.71716],
			"rotation": {"angle": -22.5, "axis": "y", "origin": [4.41758, 2.25, 9.71716]},
			"faces": {
				"north": {"uv": [14, 5.25, 10.25, 7.5], "texture": "#0"},
				"south": {"uv": [10.25, 5.25, 14, 7.5], "texture": "#0"}
			}
		},
		{
			"name": "Grass",
			"from": [7.66758, 0, 4.71716],
			"to": [15.16758, 4.5, 4.71716],
			"rotation": {"angle": -22.5, "axis": "y", "origin": [11.41758, 2.25, 4.71716]},
			"faces": {
				"north": {"uv": [14, 5.25, 10.25, 7.5], "texture": "#0"},
				"south": {"uv": [10.25, 5.25, 14, 7.5], "texture": "#0"}
			}
		},
		{
			"name": "Grass",
			"from": [5.41758, 0, 1.96716],
			"to": [5.41758, 4.5, 9.46716],
			"rotation": {"angle": 22.5, "axis": "y", "origin": [5.41758, 2.25, 5.71716]},
			"faces": {
				"east": {"uv": [14, 5.25, 10.25, 7.5], "texture": "#0"},
				"west": {"uv": [10.25, 5.25, 14, 7.5], "texture": "#0"}
			}
		},
		{
			"name": "Grass",
			"from": [8.41758, 2, 3.96716],
			"to": [8.41758, 6.5, 11.46716],
			"rotation": {"angle": 22.5, "axis": "y", "origin": [8.41758, 2.25, 7.71716]},
			"faces": {
				"east": {"uv": [14, 5.25, 10.25, 7.5], "texture": "#0"},
				"west": {"uv": [10.25, 5.25, 14, 7.5], "texture": "#0"}
			}
		}
	],
	"groups": [
		{
			"name": "Flower",
			"origin": [9.2, 14.75, 7.25],
			"children": [0, 1, 2, 3, 4, 5, 6, 7, 8, 9, 10]
		},
		{
			"name": "Flower",
			"origin": [9.2, 14.75, 7.25],
			"children": [11, 12, 13, 14, 15, 16, 17, 18, 19, 20, 21]
		},
		{
			"name": "Flower",
			"origin": [9.2, 14.75, 7.25],
			"children": [22, 23, 24, 25, 26, 27, 28, 29, 30, 31, 32]
		},
		{
			"name": "Flower",
			"origin": [9.2, 14.75, 7.25],
			"children": [33, 34, 35, 36, 37, 38, 39, 40, 41, 42, 43]
		}, 44, 45, 46, 47, 48, 49, 50, 51, 52, 53, 54, 55, 56, 57, 58, 59, 60, 61, 62, 63, 64, 65, 66, 67, 68, 69]
}
